app/__init__.py
app/__main__.py
app/config.py
app/context.py
app/grafana_client.py
app/instructions.py
app/main.py
app/patches.py
app/server.py
app/tools/__init__.py
app/tools/_label_matching.py
app/tools/admin.py
app/tools/alerting.py
app/tools/asserts.py
app/tools/availability.py
app/tools/dashboard.py
app/tools/datasources.py
app/tools/incident.py
app/tools/loki.py
app/tools/navigation.py
app/tools/oncall.py
app/tools/prometheus.py
app/tools/pyroscope.py
app/tools/search.py
app/tools/sift.py
mcp/__init__.py
mcp/server/__init__.py
mcp/server/fastmcp.py
mcp/server/streamable_http.py
grafana_fastmcp-1.3.0.dist-info/METADATA
grafana_fastmcp-1.3.0.dist-info/WHEEL
grafana_fastmcp-1.3.0.dist-info/entry_points.txt
grafana_fastmcp-1.3.0.dist-info/licenses/LICENSE
grafana_fastmcp-1.3.0.dist-info/RECORD
