Metadata-Version: 2.4
Name: grafana-fastmcp
Version: 1.3.0
Summary: Python Grafana FastMCP server/CLI with SSE, Streamable HTTP and STDIO transports
Project-URL: Homepage, https://github.com/sandersouza/grafanaFastMCP
Project-URL: Repository, https://github.com/sandersouza/grafanaFastMCP
Project-URL: Issues, https://github.com/sandersouza/grafanaFastMCP/issues
Author: Alessander de Souza Goulart
License:                                  Apache License
License-File: LICENSE
Keywords: grafana,loki,mcp,observability,oncall,prometheus,pyroscope,sift
Classifier: Environment :: Console
Classifier: Intended Audience :: Developers
Classifier: License :: OSI Approved :: Apache Software License
Classifier: Programming Language :: Python :: 3
Classifier: Programming Language :: Python :: 3 :: Only
Classifier: Programming Language :: Python :: 3.11
Classifier: Programming Language :: Python :: 3.12
Classifier: Programming Language :: Python :: 3.13
Classifier: Topic :: Software Development :: Libraries
Requires-Python: >=3.11
Requires-Dist: httpx>=0.27
Requires-Dist: mcp>=0.1.0
Requires-Dist: python-dotenv>=1.0
Requires-Dist: starlette>=0.31
Provides-Extra: sse
Requires-Dist: uvicorn>=0.30; extra == 'sse'
